vigenpy/__init__.py
vigenpy/video/__init__.py
vigenpy/video/stack_video.py
vigenpy-0.3.5.dist-info/LICENSE
vigenpy-0.3.5.dist-info/METADATA
vigenpy-0.3.5.dist-info/WHEEL
vigenpy-0.3.5.dist-info/top_level.txt
vigenpy-0.3.5.dist-info/RECORD
