Metadata-Version: 2.1
Name: vigenpy
Version: 0.3.5
Summary: A video generation library, vigenpy . It enables the developer to generate a new video by merging 2 or more videos in one video. It is a flexible library that provides you total flexibility in generating videos by stacking them. You can also use them as input to your Code. COOL.
Home-page: https://github.com/vermavinay982/vigenpy
Author: Vinay Kumar Verma
Author-email: vermavinay982@gmail.com
Maintainer: Vinay Kumar Verma
Maintainer-email: vermavinay982@gmail.com
License: MIT
Keywords: vigenpy,video gen,video,generator,computer vision,image processing
Platform: Windows
Platform: Linux
Platform: Mac OS-X
Platform: Unix
Classifier: Development Status :: 5 - Production/Stable
Classifier: Intended Audience :: Developers
Classifier: Topic :: Software Development :: Build Tools
Classifier: License :: OSI Approved :: MIT License
Classifier: Programming Language :: Python :: 3
Classifier: Programming Language :: Python :: 3.4
Classifier: Programming Language :: Python :: 3.5
Classifier: Programming Language :: Python :: 3.6
Classifier: Programming Language :: Python :: 3.7
Classifier: Programming Language :: Python :: 3.8
Requires-Python: >=3.7
License-File: LICENSE
Requires-Dist: numpy
Requires-Dist: opencv-python
Requires-Dist: tqdm
